{
  "kind": "control_family_descriptor.v1",
  "version": "v1",
  "family_id": "D7",
  "canonical_name": "cognitive-cultural",
  "display_name": "Cognitive-Cultural",
  "slug": "cognitive-cultural",
  "internal_id": "D7",
  "legacy_label": "D7-cognitive-cultural",
  "status": "active",
  "maturity": "seed",
  "classification_ref": "classification/classification-map.json",
  "specializations_ref": "specializations/index/specializations.index.json",
  "materialized_manifest_ref": "families/materialized/cognitive-cultural.manifest.json",
  "hierarchy": {
    "parent": "",
    "specializations": [
      "publication-enforcement",
      "interpretation-integrity",
      "cognitive-safety"
    ]
  },
  "resolution": {
    "default_specialization": "publication-enforcement",
    "overlay_refs": {
      "regulatory": "overlays/regulatory/index/regulatory.index.json",
      "sector": "overlays/sector/index/sector.index.json",
      "contextual": "overlays/contextual/index/contextual.index.json"
    },
    "authority_profile": {},
    "evidence_profile": {}
  },
  "applicability": {
    "domains": [
      "cognitive-cultural"
    ],
    "risk_focus": [],
    "lead_vertical": false
  },
  "hooks": {
    "policy_composition": {
      "specializations": [
        "publication-enforcement",
        "interpretation-integrity",
        "cognitive-safety"
      ],
      "legacy_seed_ref": "transitional/domain-family-seed/D7-cognitive-cultural"
    },
    "evidence": {
      "requires_policy_match_trace": false,
      "retention_hint": "standard"
    }
  },
  "source": {
    "materialized_manifest_ref": "families/materialized/cognitive-cultural.manifest.json",
    "generator": "tools/gen/build_control_family_descriptors.py"
  }
}
